ffmpegdevices/README.MD
ffmpegdevices/__init__.py
ffmpegdevices/requirements.txt
ffmpegdevices/thirdparty.json
ffmpegdevices-0.12.dist-info/LICENSE.rst
ffmpegdevices-0.12.dist-info/METADATA
ffmpegdevices-0.12.dist-info/WHEEL
ffmpegdevices-0.12.dist-info/top_level.txt
ffmpegdevices-0.12.dist-info/RECORD
