Metadata-Version: 2.1
Name: ffmpegdevices
Version: 0.12
Summary: Retrieves information about all available video and audio devices using FFmpeg.
Home-page: https://github.com/hansalemaos/ffmpegdevices
Author: Johannes Fischer
Author-email: aulasparticularesdealemaosp@gmail.com
License: MIT
Keywords: ffmpeg,devices
Classifier: Development Status :: 4 - Beta
Classifier: Programming Language :: Python :: 3 :: Only
Classifier: Programming Language :: Python :: 3.10
Classifier: Topic :: Software Development :: Libraries :: Python Modules
Classifier: Topic :: Utilities
License-File: LICENSE.rst
